<!--
 [y] hybris Platform

 Copyright (c) 2018 SAP SE or an SAP affiliate company. All rights reserved.

 This software is the confidential and proprietary information of SAP
 ("Confidential Information"). You shall not disclose such Confidential
 Information and shall use it only in accordance with the terms of the
 license agreement you entered into with SAP.
-->
<action-definition id="de.hybris.platform.apiregistrybackoffice.actions.RegisterExposedDestinationAction" xmlns:xsi="http://www.w3.org/2001/XMLSchema-instance"
                   xsi:noNamespaceSchemaLocation="http://www.hybris.com/schema/cockpitng/action-definition.xsd">

    <name>Register Exposed Destination Action</name>
    <description>Register Exposed Destination</description>
    <author>hybris</author>
    <version>0.1</version>

    <actionClassName>de.hybris.platform.apiregistrybackoffice.actions.RegisterExposedDestinationAction</actionClassName>

    <inputType>de.hybris.platform.apiregistryservices.model.ExposedDestinationModel</inputType>
    <outputType>java.lang.String</outputType>

    <iconUri>icons/icon_action_register_api_default.png</iconUri>
    <iconDisabledUri>icons/icon_action_register_api_disabled.png</iconDisabledUri>
    <iconHoverUri>icons/icon_action_register_api_hover.png</iconHoverUri>

</action-definition>


