<?xml version="1.0" encoding="UTF-8"?>
<!--
 [y] hybris Platform

 Copyright (c) 2018 SAP SE or an SAP affiliate company.  All rights reserved.

 This software is the confidential and proprietary information of SAP
 ("Confidential Information"). You shall not disclose such Confidential
 Information and shall use it only in accordance with the terms of the
 license agreement you entered into with SAP.
-->
<widget-definition xmlns:xsi="http://www.w3.org/2001/XMLSchema-instance"
	xsi:noNamespaceSchemaLocation="http://www.hybris.com/schema/cockpitng/widget-definition.xsd"
	id="com.hybris.cockpitng.outputtestwidget">

	<name>OutputTestWidget</name>
	<description>Shows all variables and their values of incoming objects.</description>
	<keywords>
		<keyword>Breadboard</keyword>
	</keywords>
	<sockets>
		<input type="java.lang.Object" id="genericInput"/>
		<input type="java.lang.Object" id="collectionInput" multiplicity="Collection"/>

	</sockets>
	<controller class="com.hybris.cockpitng.widgets.controller.OutputTestWidgetController"/>
</widget-definition>
